{
  "featured": [
    {
      "type": "Game",
      "title": "Stone King IV",
      "id": "stone-king-iv",
      "released": false,
      "releaseDate": "2020-10-02",
      "genre": "Role-playing game",
      "platform": "Desktop, Web, Unity",
      "description": "Coming soon!",
      "featuredImage": "../images/featured/sk4.jpg",
      "featuredYouTubeId": null,
      "featuredAudioFile": null,
      "site": null
    },

    {
      "type": "Game",
      "title": "Stone King III",
      "id": "stone-king-iii",
      "released": true,
      "releaseDate": "2014-10-09",
      "genre": "Role-playing game",
      "platform": "Desktop, Web, Flash",
      "description": "Explore the unknown territory of the Kingdom of Darkness. Become a powerful fighter! Earn gold and make special equipment through your skills and completling unique quests.",
      "featuredImage": "../images/featured/sk3.jpg",
      "featuredYouTubeId": null,
      "featuredAudioFile": null,
      "site": "../games/stone-king-iii"
    }
  ]
}